disk_exporter/__init__.py
disk_exporter/collector.py
disk_exporter/exporter.py
disk_exporter/getter.sh
disk_exporter/main.py
prometheus_disk_exporter-0.0.4.dist-info/LICENSE
prometheus_disk_exporter-0.0.4.dist-info/METADATA
prometheus_disk_exporter-0.0.4.dist-info/WHEEL
prometheus_disk_exporter-0.0.4.dist-info/entry_points.txt
prometheus_disk_exporter-0.0.4.dist-info/top_level.txt
prometheus_disk_exporter-0.0.4.dist-info/RECORD
