Metadata-Version: 2.1
Name: prometheus-disk-exporter
Version: 0.0.4
Summary: S.M.A.R.T. and partition data exporter for the Prometheus monitoring system
Author-email: Pietro Bonaldo Gregori <pietro.bogre@gmail.com>
License: Apache-2.0
Project-URL: Homepage, https://github.com/pbogre/prometheus-disk-exporter
Keywords: metrics,disk,prometheus,exporter,monitoring,smart
Classifier: Programming Language :: Python :: 3
Classifier: Topic :: System :: Monitoring
Classifier: Intended Audience :: System Administrators
Classifier: Operating System :: POSIX :: Linux
Requires-Python: >=3.11
License-File: LICENSE
Requires-Dist: prometheus-client >=0.19.0
